{"data":{"mal_id":32259,"url":"https://myanimelist.net/anime/32259/Mahou_no_Tenshi_Creamy_Mami__Perfect_Memory","images":{"jpg":{"image_url":"https://cdn.myanimelist.net/images/anime/8/77437.jpg","small_image_url":"https://cdn.myanimelist.net/images/anime/8/77437t.jpg","large_image_url":"https://cdn.myanimelist.net/images/anime/8/77437l.jpg"},"webp":{"image_url":"https://cdn.myanimelist.net/images/anime/8/77437.webp","small_image_url":"https://cdn.myanimelist.net/images/anime/8/77437t.webp","large_image_url":"https://cdn.myanimelist.net/images/anime/8/77437l.webp"}},"trailer":{"youtube_id":null,"url":null,"embed_url":null,"images":{"image_url":null,"small_image_url":null,"medium_image_url":null,"large_image_url":null,"maximum_image_url":null}},"approved":true,"titles":[{"type":"Default","title":"Mahou no Tenshi Creamy Mami: Perfect Memory"},{"type":"Japanese","title":"魔法の天使 クリィミーマミ パーフェクトメモリー"}],"title":"Mahou no Tenshi Creamy Mami: Perfect Memory","title_english":null,"title_japanese":"魔法の天使 クリィミーマミ パーフェクトメモリー","title_synonyms":[],"type":"OVA","source":"Original","episodes":1,"status":"Finished Airing","airing":false,"aired":{"from":"1987-03-28T00:00:00+00:00","to":null,"prop":{"from":{"day":28,"month":3,"year":1987},"to":{"day":null,"month":null,"year":null}},"string":"Mar 28, 1987"},"duration":"1 min","rating":"G - All Ages","score":5.64,"scored_by":150,"rank":11083,"popularity":13759,"members":615,"favorites":0,"synopsis":"An OVA supercut of Eien no Once More, Long Goodbye, and Curtain Call. One new animated feature is a fake Creamy Mami commercial for Creamy Soap. The feature then goes on to promote the Majokko Club Yoningumi: A Kuukan kara no Alien X release for later that year. This entry will only reflect the new footage.","background":null,"season":null,"year":null,"broadcast":{"day":null,"time":null,"timezone":null,"string":null},"producers":[],"licensors":[],"studios":[{"mal_id":1,"type":"anime","name":"Pierrot","url":"https://myanimelist.net/anime/producer/1/Pierrot"}],"genres":[{"mal_id":36,"type":"anime","name":"Slice of Life","url":"https://myanimelist.net/anime/genre/36/Slice_of_Life"}],"explicit_genres":[],"themes":[{"mal_id":20,"type":"anime","name":"Parody","url":"https://myanimelist.net/anime/genre/20/Parody"}],"demographics":[{"mal_id":25,"type":"anime","name":"Shoujo","url":"https://myanimelist.net/anime/genre/25/Shoujo"}],"relations":[{"relation":"Parent story","entry":[{"mal_id":2038,"type":"anime","name":"Mahou no Star Magical Emi","url":"https://myanimelist.net/anime/2038/Mahou_no_Star_Magical_Emi"},{"mal_id":2039,"type":"anime","name":"Mahou no Yousei Persia","url":"https://myanimelist.net/anime/2039/Mahou_no_Yousei_Persia"},{"mal_id":2044,"type":"anime","name":"Mahou no Tenshi Creamy Mami","url":"https://myanimelist.net/anime/2044/Mahou_no_Tenshi_Creamy_Mami"},{"mal_id":2080,"type":"anime","name":"Majokko Club Yoningumi: A Kuukan kara no Alien X","url":"https://myanimelist.net/anime/2080/Majokko_Club_Yoningumi__A_Kuukan_kara_no_Alien_X"},{"mal_id":3660,"type":"anime","name":"Mahou no Idol Pastel Yumi","url":"https://myanimelist.net/anime/3660/Mahou_no_Idol_Pastel_Yumi"}]}],"theme":{"openings":[],"endings":[]},"external":[],"streaming":[]}}