{"data":{"mal_id":36559,"url":"https://myanimelist.net/anime/36559/Zukkoke_Sannin-gumi__Kusunoki_Yashiki_no_Guruguru-sama","images":{"jpg":{"image_url":"https://cdn.myanimelist.net/images/anime/13/88358.jpg","small_image_url":"https://cdn.myanimelist.net/images/anime/13/88358t.jpg","large_image_url":"https://cdn.myanimelist.net/images/anime/13/88358l.jpg"},"webp":{"image_url":"https://cdn.myanimelist.net/images/anime/13/88358.webp","small_image_url":"https://cdn.myanimelist.net/images/anime/13/88358t.webp","large_image_url":"https://cdn.myanimelist.net/images/anime/13/88358l.webp"}},"trailer":{"youtube_id":null,"url":null,"embed_url":null,"images":{"image_url":null,"small_image_url":null,"medium_image_url":null,"large_image_url":null,"maximum_image_url":null}},"approved":true,"titles":[{"type":"Default","title":"Zukkoke Sannin-gumi: Kusunoki Yashiki no Guruguru-sama"},{"type":"Japanese","title":"ズッコケ三人組 楠屋敷のグルグル様"}],"title":"Zukkoke Sannin-gumi: Kusunoki Yashiki no Guruguru-sama","title_english":null,"title_japanese":"ズッコケ三人組 楠屋敷のグルグル様","title_synonyms":[],"type":"Special","source":"Unknown","episodes":1,"status":"Finished Airing","airing":false,"aired":{"from":"1995-11-11T00:00:00+00:00","to":null,"prop":{"from":{"day":11,"month":11,"year":1995},"to":{"day":null,"month":null,"year":null}},"string":"Nov 11, 1995"},"duration":"45 min","rating":"PG - Children","score":null,"scored_by":null,"rank":21981,"popularity":17171,"members":257,"favorites":0,"synopsis":null,"background":null,"season":null,"year":null,"broadcast":{"day":null,"time":null,"timezone":null,"string":null},"producers":[{"mal_id":1003,"type":"anime","name":"Nippon Television Network","url":"https://myanimelist.net/anime/producer/1003/Nippon_Television_Network"}],"licensors":[],"studios":[{"mal_id":7,"type":"anime","name":"J.C.Staff","url":"https://myanimelist.net/anime/producer/7/JCStaff"}],"genres":[],"explicit_genres":[],"themes":[{"mal_id":6,"type":"anime","name":"Mythology","url":"https://myanimelist.net/anime/genre/6/Mythology"}],"demographics":[{"mal_id":15,"type":"anime","name":"Kids","url":"https://myanimelist.net/anime/genre/15/Kids"}],"relations":[{"relation":"Other","entry":[{"mal_id":11497,"type":"anime","name":"Sore Ike! Zukkoke Sannin-gumi","url":"https://myanimelist.net/anime/11497/Sore_Ike_Zukkoke_Sannin-gumi"}]}],"theme":{"openings":[],"endings":[]},"external":[],"streaming":[]}}