{"data":{"mal_id":39367,"url":"https://myanimelist.net/anime/39367/Ganbare_Kobo-chan_Gyuunyuu","images":{"jpg":{"image_url":"https://cdn.myanimelist.net/images/anime/1403/99397.jpg","small_image_url":"https://cdn.myanimelist.net/images/anime/1403/99397t.jpg","large_image_url":"https://cdn.myanimelist.net/images/anime/1403/99397l.jpg"},"webp":{"image_url":"https://cdn.myanimelist.net/images/anime/1403/99397.webp","small_image_url":"https://cdn.myanimelist.net/images/anime/1403/99397t.webp","large_image_url":"https://cdn.myanimelist.net/images/anime/1403/99397l.webp"}},"trailer":{"youtube_id":null,"url":null,"embed_url":null,"images":{"image_url":null,"small_image_url":null,"medium_image_url":null,"large_image_url":null,"maximum_image_url":null}},"approved":true,"titles":[{"type":"Default","title":"Ganbare! Kobo-chan Gyuunyuu"},{"type":"Japanese","title":"がんばれ！コボちゃん牛乳"}],"title":"Ganbare! Kobo-chan Gyuunyuu","title_english":null,"title_japanese":"がんばれ！コボちゃん牛乳","title_synonyms":[],"type":"OVA","source":"4-koma manga","episodes":1,"status":"Finished Airing","airing":false,"aired":{"from":null,"to":null,"prop":{"from":{"day":null,"month":null,"year":null},"to":{"day":null,"month":null,"year":null}},"string":"Not available"},"duration":"Unknown","rating":"G - All Ages","score":null,"scored_by":null,"rank":19048,"popularity":19718,"members":105,"favorites":0,"synopsis":"An educational anime explaining trademarks to children using the cast of Kobo-chan commissioned by the Japan Patent Office.","background":null,"season":null,"year":null,"broadcast":{"day":null,"time":null,"timezone":null,"string":null},"producers":[],"licensors":[],"studios":[],"genres":[],"explicit_genres":[],"themes":[],"demographics":[{"mal_id":15,"type":"anime","name":"Kids","url":"https://myanimelist.net/anime/genre/15/Kids"}],"relations":[{"relation":"Adaptation","entry":[{"mal_id":22910,"type":"manga","name":"Kobo-chan","url":"https://myanimelist.net/manga/22910/Kobo-chan"}]},{"relation":"Character","entry":[{"mal_id":19585,"type":"anime","name":"Kobo-chan","url":"https://myanimelist.net/anime/19585/Kobo-chan"}]}],"theme":{"openings":[],"endings":[]},"external":[],"streaming":[]}}