{"data":{"mal_id":42451,"url":"https://myanimelist.net/anime/42451/Mario_Kirby_Meisaku_Video","images":{"jpg":{"image_url":"https://cdn.myanimelist.net/images/anime/1138/108472.jpg","small_image_url":"https://cdn.myanimelist.net/images/anime/1138/108472t.jpg","large_image_url":"https://cdn.myanimelist.net/images/anime/1138/108472l.jpg"},"webp":{"image_url":"https://cdn.myanimelist.net/images/anime/1138/108472.webp","small_image_url":"https://cdn.myanimelist.net/images/anime/1138/108472t.webp","large_image_url":"https://cdn.myanimelist.net/images/anime/1138/108472l.webp"}},"trailer":{"youtube_id":null,"url":null,"embed_url":null,"images":{"image_url":null,"small_image_url":null,"medium_image_url":null,"large_image_url":null,"maximum_image_url":null}},"approved":true,"titles":[{"type":"Default","title":"Mario Kirby Meisaku Video"},{"type":"Synonym","title":"Mario Kirby Masterpiece Video"},{"type":"Japanese","title":"マリオ・カービィ 名作ビデオ"}],"title":"Mario Kirby Meisaku Video","title_english":null,"title_japanese":"マリオ・カービィ 名作ビデオ","title_synonyms":["Mario Kirby Masterpiece Video"],"type":"OVA","source":"Game","episodes":1,"status":"Finished Airing","airing":false,"aired":{"from":"1993-01-01T00:00:00+00:00","to":null,"prop":{"from":{"day":1,"month":1,"year":1993},"to":{"day":null,"month":null,"year":null}},"string":"1993"},"duration":"18 min","rating":"PG - Children","score":5.2,"scored_by":208,"rank":12483,"popularity":12977,"members":792,"favorites":1,"synopsis":"An educational video only released in Japan, and stars Mario and Kirby, both on their own separate adventures. It is aimed at teaching young children Kanji/Chinese characters.\n\n(Source: Kirby Wiki)","background":"The video is narrated by Mayumi Tanaka, who also voices the characters. It is also worth noting that this is the first time Kirby was given a voice.","season":null,"year":null,"broadcast":{"day":null,"time":null,"timezone":null,"string":null},"producers":[{"mal_id":1430,"type":"anime","name":"Shogakukan","url":"https://myanimelist.net/anime/producer/1430/Shogakukan"}],"licensors":[],"studios":[],"genres":[{"mal_id":2,"type":"anime","name":"Adventure","url":"https://myanimelist.net/anime/genre/2/Adventure"},{"mal_id":10,"type":"anime","name":"Fantasy","url":"https://myanimelist.net/anime/genre/10/Fantasy"}],"explicit_genres":[],"themes":[],"demographics":[{"mal_id":15,"type":"anime","name":"Kids","url":"https://myanimelist.net/anime/genre/15/Kids"}],"relations":[{"relation":"Character","entry":[{"mal_id":2390,"type":"anime","name":"Hoshi no Kirby","url":"https://myanimelist.net/anime/2390/Hoshi_no_Kirby"},{"mal_id":3886,"type":"anime","name":"Super Mario Brothers: Peach-hime Kyuushutsu Daisakusen!","url":"https://myanimelist.net/anime/3886/Super_Mario_Brothers__Peach-hime_Kyuushutsu_Daisakusen"}]}],"theme":{"openings":[],"endings":[]},"external":[],"streaming":[]}}