{"data":{"mal_id":45474,"url":"https://myanimelist.net/anime/45474/Mofa_Senlin_Da_Maoxian","images":{"jpg":{"image_url":"https://cdn.myanimelist.net/images/anime/1330/129505.jpg","small_image_url":"https://cdn.myanimelist.net/images/anime/1330/129505t.jpg","large_image_url":"https://cdn.myanimelist.net/images/anime/1330/129505l.jpg"},"webp":{"image_url":"https://cdn.myanimelist.net/images/anime/1330/129505.webp","small_image_url":"https://cdn.myanimelist.net/images/anime/1330/129505t.webp","large_image_url":"https://cdn.myanimelist.net/images/anime/1330/129505l.webp"}},"trailer":{"youtube_id":null,"url":null,"embed_url":null,"images":{"image_url":null,"small_image_url":null,"medium_image_url":null,"large_image_url":null,"maximum_image_url":null}},"approved":true,"titles":[{"type":"Default","title":"Mofa Senlin Da Maoxian"},{"type":"Japanese","title":"魔法森林大冒险"}],"title":"Mofa Senlin Da Maoxian","title_english":null,"title_japanese":"魔法森林大冒险","title_synonyms":[],"type":"ONA","source":"Original","episodes":52,"status":"Finished Airing","airing":false,"aired":{"from":null,"to":null,"prop":{"from":{"day":null,"month":null,"year":null},"to":{"day":null,"month":null,"year":null}},"string":"Not available"},"duration":"5 min per ep","rating":"PG - Children","score":null,"scored_by":null,"rank":14584,"popularity":23479,"members":22,"favorites":0,"synopsis":null,"background":null,"season":null,"year":null,"broadcast":{"day":null,"time":null,"timezone":null,"string":null},"producers":[],"licensors":[],"studios":[],"genres":[{"mal_id":10,"type":"anime","name":"Fantasy","url":"https://myanimelist.net/anime/genre/10/Fantasy"}],"explicit_genres":[],"themes":[{"mal_id":51,"type":"anime","name":"Anthropomorphic","url":"https://myanimelist.net/anime/genre/51/Anthropomorphic"}],"demographics":[{"mal_id":15,"type":"anime","name":"Kids","url":"https://myanimelist.net/anime/genre/15/Kids"}],"relations":[{"relation":"Character","entry":[{"mal_id":45470,"type":"anime","name":"Hei! Xingxing Hu","url":"https://myanimelist.net/anime/45470/Hei_Xingxing_Hu"}]}],"theme":{"openings":[],"endings":[]},"external":[],"streaming":[]}}