{"data":{"mal_id":46712,"url":"https://myanimelist.net/anime/46712/Jingling_Ai_Ya_Jiangtang","images":{"jpg":{"image_url":"https://cdn.myanimelist.net/images/anime/1727/131126.jpg","small_image_url":"https://cdn.myanimelist.net/images/anime/1727/131126t.jpg","large_image_url":"https://cdn.myanimelist.net/images/anime/1727/131126l.jpg"},"webp":{"image_url":"https://cdn.myanimelist.net/images/anime/1727/131126.webp","small_image_url":"https://cdn.myanimelist.net/images/anime/1727/131126t.webp","large_image_url":"https://cdn.myanimelist.net/images/anime/1727/131126l.webp"}},"trailer":{"youtube_id":null,"url":null,"embed_url":null,"images":{"image_url":null,"small_image_url":null,"medium_image_url":null,"large_image_url":null,"maximum_image_url":null}},"approved":true,"titles":[{"type":"Default","title":"Jingling Ai Ya Jiangtang"},{"type":"Japanese","title":"精灵爱牙讲堂"}],"title":"Jingling Ai Ya Jiangtang","title_english":null,"title_japanese":"精灵爱牙讲堂","title_synonyms":[],"type":"ONA","source":"Original","episodes":20,"status":"Finished Airing","airing":false,"aired":{"from":null,"to":null,"prop":{"from":{"day":null,"month":null,"year":null},"to":{"day":null,"month":null,"year":null}},"string":"Not available"},"duration":"3 min per ep","rating":"PG - Children","score":null,"scored_by":null,"rank":20085,"popularity":23727,"members":21,"favorites":0,"synopsis":null,"background":null,"season":null,"year":null,"broadcast":{"day":null,"time":null,"timezone":null,"string":null},"producers":[],"licensors":[],"studios":[],"genres":[],"explicit_genres":[],"themes":[],"demographics":[{"mal_id":15,"type":"anime","name":"Kids","url":"https://myanimelist.net/anime/genre/15/Kids"}],"relations":[{"relation":"Character","entry":[{"mal_id":46713,"type":"anime","name":"Jingling Ai Ya Jiangtang: Kouqiang Jiankang Zhishi","url":"https://myanimelist.net/anime/46713/Jingling_Ai_Ya_Jiangtang__Kouqiang_Jiankang_Zhishi"},{"mal_id":46714,"type":"anime","name":"Yaya Jingling Zhandui","url":"https://myanimelist.net/anime/46714/Yaya_Jingling_Zhandui"}]}],"theme":{"openings":[],"endings":[]},"external":[],"streaming":[]}}