{"data":{"mal_id":52285,"url":"https://myanimelist.net/anime/52285/Mirai_Millennium","images":{"jpg":{"image_url":"https://cdn.myanimelist.net/images/anime/1296/124924.jpg","small_image_url":"https://cdn.myanimelist.net/images/anime/1296/124924t.jpg","large_image_url":"https://cdn.myanimelist.net/images/anime/1296/124924l.jpg"},"webp":{"image_url":"https://cdn.myanimelist.net/images/anime/1296/124924.webp","small_image_url":"https://cdn.myanimelist.net/images/anime/1296/124924t.webp","large_image_url":"https://cdn.myanimelist.net/images/anime/1296/124924l.webp"}},"trailer":{"youtube_id":null,"url":null,"embed_url":null,"images":{"image_url":null,"small_image_url":null,"medium_image_url":null,"large_image_url":null,"maximum_image_url":null}},"approved":false,"titles":[{"type":"Default","title":"Mirai Millennium"},{"type":"Synonym","title":"Mirai Millennium OP"},{"type":"Japanese","title":"ミライミレニアム"}],"title":"Mirai Millennium","title_english":null,"title_japanese":"ミライミレニアム","title_synonyms":["Mirai Millennium OP"],"type":"Music","source":"Original","episodes":1,"status":"Finished Airing","airing":false,"aired":{"from":"2011-09-27T00:00:00+00:00","to":null,"prop":{"from":{"day":27,"month":9,"year":2011},"to":{"day":null,"month":null,"year":null}},"string":"Sep 27, 2011"},"duration":"1 hr 38 min","rating":null,"score":null,"scored_by":null,"rank":0,"popularity":0,"members":0,"favorites":0,"synopsis":"Opening for Danny Choo’s Mirai Millennium anime project and also for the second season of Culture Japan, co-animated by J.C.Staff and Danny Choo’s Mirai Fusion.","background":null,"season":null,"year":null,"broadcast":{"day":null,"time":null,"timezone":null,"string":null},"producers":[],"licensors":[],"studios":[],"genres":[],"explicit_genres":[],"themes":[],"demographics":[],"relations":[],"theme":{"openings":[],"endings":[]},"external":[],"streaming":[]}}