{"data":{"mal_id":52577,"url":"https://myanimelist.net/anime/52577/Zhen_Dao_Ge_2nd_Season","images":{"jpg":{"image_url":"https://cdn.myanimelist.net/images/anime/1147/126432.jpg","small_image_url":"https://cdn.myanimelist.net/images/anime/1147/126432t.jpg","large_image_url":"https://cdn.myanimelist.net/images/anime/1147/126432l.jpg"},"webp":{"image_url":"https://cdn.myanimelist.net/images/anime/1147/126432.webp","small_image_url":"https://cdn.myanimelist.net/images/anime/1147/126432t.webp","large_image_url":"https://cdn.myanimelist.net/images/anime/1147/126432l.webp"}},"trailer":{"youtube_id":null,"url":null,"embed_url":null,"images":{"image_url":null,"small_image_url":null,"medium_image_url":null,"large_image_url":null,"maximum_image_url":null}},"approved":false,"titles":[{"type":"Default","title":"Zhen Dao Ge 2nd Season"},{"type":"Japanese","title":"枕刀歌 第2季"}],"title":"Zhen Dao Ge 2nd Season","title_english":null,"title_japanese":"枕刀歌 第2季","title_synonyms":[],"type":"ONA","source":"Original","episodes":null,"status":"Not yet aired","airing":false,"aired":{"from":"2022-01-01T00:00:00+00:00","to":null,"prop":{"from":{"day":1,"month":1,"year":2022},"to":{"day":null,"month":null,"year":null}},"string":"2022 to ?"},"duration":"Unknown","rating":"PG-13 - Teens 13 or older","score":null,"scored_by":null,"rank":0,"popularity":0,"members":0,"favorites":0,"synopsis":null,"background":null,"season":null,"year":null,"broadcast":{"day":null,"time":null,"timezone":null,"string":null},"producers":[],"licensors":[],"studios":[],"genres":[{"mal_id":1,"type":"anime","name":"Action","url":"https://myanimelist.net/anime/genre/1/Action"},{"mal_id":2,"type":"anime","name":"Adventure","url":"https://myanimelist.net/anime/genre/2/Adventure"}],"explicit_genres":[],"themes":[{"mal_id":17,"type":"anime","name":"Martial Arts","url":"https://myanimelist.net/anime/genre/17/Martial_Arts"}],"demographics":[],"relations":[{"relation":"Prequel","entry":[{"mal_id":48914,"type":"anime","name":"Zhen Dao Ge: Chenshi Hang","url":"https://myanimelist.net/anime/48914/Zhen_Dao_Ge__Chenshi_Hang"}]}],"theme":{"openings":[],"endings":[]},"external":[],"streaming":[]}}