{"data":{"mal_id":53649,"url":"https://myanimelist.net/anime/53649/Rat_a_Tat_Writer","images":{"jpg":{"image_url":"https://cdn.myanimelist.net/images/anime/1903/131370.jpg","small_image_url":"https://cdn.myanimelist.net/images/anime/1903/131370t.jpg","large_image_url":"https://cdn.myanimelist.net/images/anime/1903/131370l.jpg"},"webp":{"image_url":"https://cdn.myanimelist.net/images/anime/1903/131370.webp","small_image_url":"https://cdn.myanimelist.net/images/anime/1903/131370t.webp","large_image_url":"https://cdn.myanimelist.net/images/anime/1903/131370l.webp"}},"trailer":{"youtube_id":null,"url":null,"embed_url":null,"images":{"image_url":null,"small_image_url":null,"medium_image_url":null,"large_image_url":null,"maximum_image_url":null}},"approved":true,"titles":[{"type":"Default","title":"Rat a Tat Writer"},{"type":"Japanese","title":"RAT A TAT WRITER"}],"title":"Rat a Tat Writer","title_english":null,"title_japanese":"RAT A TAT WRITER","title_synonyms":[],"type":"Music","source":"Original","episodes":1,"status":"Finished Airing","airing":false,"aired":{"from":"2022-11-16T00:00:00+00:00","to":null,"prop":{"from":{"day":16,"month":11,"year":2022},"to":{"day":null,"month":null,"year":null}},"string":"Nov 16, 2022"},"duration":"3 min","rating":"PG-13 - Teens 13 or older","score":null,"scored_by":null,"rank":15708,"popularity":19757,"members":103,"favorites":0,"synopsis":null,"background":null,"season":null,"year":null,"broadcast":{"day":null,"time":null,"timezone":null,"string":null},"producers":[],"licensors":[],"studios":[],"genres":[],"explicit_genres":[],"themes":[{"mal_id":19,"type":"anime","name":"Music","url":"https://myanimelist.net/anime/genre/19/Music"}],"demographics":[],"relations":[{"relation":"Character","entry":[{"mal_id":49527,"type":"anime","name":"Princess♂","url":"https://myanimelist.net/anime/49527/Princess♂"}]}],"theme":{"openings":[],"endings":[]},"external":[],"streaming":[]}}