{"data":{"mal_id":5878,"url":"https://myanimelist.net/anime/5878/Love_Position__Halley_Densetsu","images":{"jpg":{"image_url":"https://cdn.myanimelist.net/images/anime/9/12399.jpg","small_image_url":"https://cdn.myanimelist.net/images/anime/9/12399t.jpg","large_image_url":"https://cdn.myanimelist.net/images/anime/9/12399l.jpg"},"webp":{"image_url":"https://cdn.myanimelist.net/images/anime/9/12399.webp","small_image_url":"https://cdn.myanimelist.net/images/anime/9/12399t.webp","large_image_url":"https://cdn.myanimelist.net/images/anime/9/12399l.webp"}},"trailer":{"youtube_id":null,"url":null,"embed_url":null,"images":{"image_url":null,"small_image_url":null,"medium_image_url":null,"large_image_url":null,"maximum_image_url":null}},"approved":true,"titles":[{"type":"Default","title":"Love Position: Halley Densetsu"},{"type":"Synonym","title":"Love Position"},{"type":"Synonym","title":"Legend of the Halley"},{"type":"Japanese","title":"ラブ・ポジション　ハレー伝説"}],"title":"Love Position: Halley Densetsu","title_english":null,"title_japanese":"ラブ・ポジション　ハレー伝説","title_synonyms":["Love Position","Legend of the Halley"],"type":"OVA","source":"Unknown","episodes":1,"status":"Finished Airing","airing":false,"aired":{"from":"1985-12-16T00:00:00+00:00","to":null,"prop":{"from":{"day":16,"month":12,"year":1985},"to":{"day":null,"month":null,"year":null}},"string":"Dec 16, 1985"},"duration":"1 hr 33 min","rating":"PG-13 - Teens 13 or older","score":5.56,"scored_by":403,"rank":11368,"popularity":11528,"members":1296,"favorites":2,"synopsis":"The very first original animated video produced by Tezuka Productions about an agent who was sent riding on Halley's comet to the Earth. He was actually, though, given the order to destroy the Earth. Captivated by planet's beauty, however, he is no longer able to destroy the planet. Seventy-six years later, another agent from Halley's comet is sent to the earth to liquidate this traitor, who is now disguised as a girl named Lamina in Vietnam. Tezuka Osamu oversaw only the original story.\n\n(Source: AniDB)","background":null,"season":null,"year":null,"broadcast":{"day":null,"time":null,"timezone":null,"string":null},"producers":[{"mal_id":200,"type":"anime","name":"Tezuka Productions","url":"https://myanimelist.net/anime/producer/200/Tezuka_Productions"}],"licensors":[],"studios":[],"genres":[{"mal_id":10,"type":"anime","name":"Fantasy","url":"https://myanimelist.net/anime/genre/10/Fantasy"},{"mal_id":24,"type":"anime","name":"Sci-Fi","url":"https://myanimelist.net/anime/genre/24/Sci-Fi"}],"explicit_genres":[],"themes":[],"demographics":[],"relations":[],"theme":{"openings":[],"endings":["\"Sugao no mama de (素顔のままで)\" by Nagayama Youko"]},"external":[],"streaming":[]}}